rxinfer/__init__.py
rxinfer-0.0.1.dist-info/METADATA
rxinfer-0.0.1.dist-info/WHEEL
rxinfer-0.0.1.dist-info/RECORD
