Metadata-Version: 2.4
Name: RxInfer
Version: 0.0.1
Summary: The official Python library for RxInfer
Project-URL: Homepage, https://github.com/lazydynamics/RxInfer.py
Project-URL: Repository, https://github.com/lazydynamics/RxInfer.py
Project-URL: Issues, https://github.com/lazydynamics/RxInfer.py/issues
Author-email: Lazy Dynamics <info@lazydynamics.com>
License-Expression: Apache-2.0
Classifier: Intended Audience :: Developers
Classifier: License :: OSI Approved :: Apache Software License
Classifier: Operating System :: OS Independent
Classifier: Programming Language :: Python :: 3
Classifier: Typing :: Typed
Requires-Python: >=3.9
Provides-Extra: dev
Requires-Dist: hatchling; extra == 'dev'
Requires-Dist: mypy; extra == 'dev'
